LengthConversion/__init__.py
LengthConversion/main.py
lengthconversion-1.0.dist-info/METADATA
lengthconversion-1.0.dist-info/WHEEL
lengthconversion-1.0.dist-info/top_level.txt
lengthconversion-1.0.dist-info/RECORD
