Metadata-Version: 2.4
Name: LengthConversion
Version: 1.0
Summary: Module That Lets You Convert Units Of Length In Easy Way.
Dynamic: summary
